AUTHORS.rst
CONTRIBUTING.rst
HISTORY.rst
LICENSE
MANIFEST.in
README.rst
requirements.txt
setup.cfg
setup.py
versioneer.py
clsify/__init__.py
clsify/__main__.py
clsify/_version.py
clsify/blast.py
clsify/cli.py
clsify/conversion.py
clsify/export.py
clsify/haplotyping.py
clsify/workflow.py
clsify.egg-info/PKG-INFO
clsify.egg-info/SOURCES.txt
clsify.egg-info/dependency_links.txt
clsify.egg-info/entry_points.txt
clsify.egg-info/not-zip-safe
clsify.egg-info/requires.txt
clsify.egg-info/top_level.txt
clsify/data/.haplotype_table.txt.swp
clsify/data/EU812559.1.fasta
clsify/data/EU812559.1.fasta.fai
clsify/data/EU812559.1.fasta.nhr
clsify/data/EU812559.1.fasta.nin
clsify/data/EU812559.1.fasta.nsq
clsify/data/EU834131.1.fasta
clsify/data/EU834131.1.fasta.fai
clsify/data/EU834131.1.fasta.nhr
clsify/data/EU834131.1.fasta.nin
clsify/data/EU834131.1.fasta.nsq
clsify/data/haplotype_table.txt
clsify/data/haplotype_table.txt~
clsify/web/__init__.py
clsify/web/app.py
clsify/web/callbacks.py
clsify/web/settings.py
clsify/web/ui.py
clsify/web/assets/bootstrap.min.css
clsify/web/assets/clsify.css
clsify/web/assets/clsify_example.zip
clsify/web/assets/fontawesome/css/all.min.css
clsify/web/assets/fontawesome/webfonts/fa-brands-400.eot
clsify/web/assets/fontawesome/webfonts/fa-brands-400.svg
clsify/web/assets/fontawesome/webfonts/fa-brands-400.ttf
clsify/web/assets/fontawesome/webfonts/fa-brands-400.woff
clsify/web/assets/fontawesome/webfonts/fa-brands-400.woff2
clsify/web/assets/fontawesome/webfonts/fa-regular-400.eot
clsify/web/assets/fontawesome/webfonts/fa-regular-400.svg
clsify/web/assets/fontawesome/webfonts/fa-regular-400.ttf
clsify/web/assets/fontawesome/webfonts/fa-regular-400.woff
clsify/web/assets/fontawesome/webfonts/fa-regular-400.woff2
clsify/web/assets/fontawesome/webfonts/fa-solid-900.eot
clsify/web/assets/fontawesome/webfonts/fa-solid-900.svg
clsify/web/assets/fontawesome/webfonts/fa-solid-900.ttf
clsify/web/assets/fontawesome/webfonts/fa-solid-900.woff
clsify/web/assets/fontawesome/webfonts/fa-solid-900.woff2
requirements/base.txt
requirements/dev.txt
requirements/test.txt
requirements/test_black.txt
tests/__init__.py