Metadata-Version: 1.1
Name: clsify
Version: 0.1.1
Summary: Classify C. Liberibacter solanacearum haplotypes
Home-page: https://github.com/holtgrewe/clsify
Author: Manuel Holtgrewe
Author-email: manuel.holtgrewe@bihealth.de
License: MIT license
Keywords: clsify
Platform: UNKNOWN
Classifier: Development Status :: 2 - Pre-Alpha
Classifier: Intended Audience :: Developers
Classifier: License :: OSI Approved :: MIT License
Classifier: Natural Language :: English
Classifier: Programming Language :: Python :: 3
Classifier: Programming Language :: Python :: 3.6
Classifier: Programming Language :: Python :: 3.7
Classifier: Programming Language :: Python :: 3.8
